pin_builder/__init__.py
pin_builder/build_backend.py
pin_builder-0.3.dist-info/LICENSE
pin_builder-0.3.dist-info/WHEEL
pin_builder-0.3.dist-info/METADATA
pin_builder-0.3.dist-info/RECORD
