Metadata-Version: 2.1
Name: pin_builder
Version: 0.3
Summary: Test build backend
Author-email: ilia cherezov <cherezov.ia@phystech.edu>
Classifier: License :: OSI Approved :: MIT License
Requires-Dist: setuptools
